odoo/addons/l10n_ro_city/README.rst
odoo/addons/l10n_ro_city/__init__.py
odoo/addons/l10n_ro_city/__manifest__.py
odoo/addons/l10n_ro_city/data/res.country.state.csv
odoo/addons/l10n_ro_city/data/res_city.xml
odoo/addons/l10n_ro_city/i18n/l10n_ro_city.pot
odoo/addons/l10n_ro_city/i18n/ro.po
odoo/addons/l10n_ro_city/migrations/14.0.2.0.0/pre-migration.py
odoo/addons/l10n_ro_city/migrations/14.0.2.1.1/pre-migration.py
odoo/addons/l10n_ro_city/models/__init__.py
odoo/addons/l10n_ro_city/models/res_city.py
odoo/addons/l10n_ro_city/models/res_country_state.py
odoo/addons/l10n_ro_city/models/res_partner.py
odoo/addons/l10n_ro_city/readme/CONTRIBUTORS.rst
odoo/addons/l10n_ro_city/readme/DESCRIPTION.rst
odoo/addons/l10n_ro_city/static/description/icon.png
odoo/addons/l10n_ro_city/static/description/icon.svg
odoo/addons/l10n_ro_city/static/description/index.html
odoo/addons/l10n_ro_city/tests/__init__.py
odoo/addons/l10n_ro_city/tests/test_ro_city.py
odoo/addons/l10n_ro_city/views/res_city_view.xml
odoo14_addon_l10n_ro_city-14.0.3.4.0.dist-info/METADATA
odoo14_addon_l10n_ro_city-14.0.3.4.0.dist-info/WHEEL
odoo14_addon_l10n_ro_city-14.0.3.4.0.dist-info/top_level.txt
odoo14_addon_l10n_ro_city-14.0.3.4.0.dist-info/RECORD
